{
    "weeks": [
        {
            "week": "Week 1",
            "links": [
                {
                    "url": "week01/holygrail.html",
                    "title": "HolyGrail"
                },

                {
                    "url": "https://codepen.io/Luis-Andrade-the-flexboxer/pen/abPLOKY",
                    "title": "JS Practice"
                },

                {
                    "url": "week01/media-query.html",
                    "title": "Media Query"
                },

                {
                    "url": "week01/chamber-site-plan.html",
                    "title": "Chamber Commerce Site-plan"
                }

            ]

        },

        {
            "week": "Week 2",
            "links": [
                {
                    "url": "week02/design.html",
                    "title": "Design Principles"
                },

                {
                    "url": "https://codepen.io/Luis-Andrade-the-flexboxer/pen/bGOLOZo",
                    "title": "Responsive Navigation"
                },

                {
                    "url": "week02/bom.html",
                    "title": "DOM Manipulation"
                }
              
            ]
        },

        {
            "week": "Week 3",
            "links": [
             
            ]
        },

        {
            "week": "Week 4",
            "links": [
         
            ]
        },

        {
            "week": "Week 5",
            "links": [
         
            ]
        }
    ]
}